sleepstudyparser/SleepStudyParser.py
sleepstudyparser/__init__.py
sleepstudyparser/constants/BlockerType.py
sleepstudyparser/constants/ModernStandbyType.py
sleepstudyparser/constants/SessionType.py
sleepstudyparser/constants/__init__.py
sleepstudyparser/objects/Drips.py
sleepstudyparser/objects/Report.py
sleepstudyparser/objects/State.py
sleepstudyparser/objects/TopOffender.py
sleepstudyparser/objects/__init__.py
sleepstudyparser/static/img.png
sleepstudyparser-0.1.0.dist-info/WHEEL
sleepstudyparser-0.1.0.dist-info/METADATA
sleepstudyparser-0.1.0.dist-info/RECORD
