Metadata-Version: 2.1
Name: sleepstudyparser
Version: 0.1.0
Summary: 
Home-page: https://github.com/Dibakarroy1997/sleepstudyparser
Keywords: sleepstudy,windows11
Author: debakarr
Author-email: debakar.roy@outlook.com
Requires-Python: >=3.8,<4.0
Classifier: Programming Language :: Python :: 3
Classifier: Programming Language :: Python :: 3.10
Classifier: Programming Language :: Python :: 3.8
Classifier: Programming Language :: Python :: 3.9
Project-URL: Repository, https://github.com/Dibakarroy1997/sleepstudyparser
